{
  "bat_2026": [
    {
      "Name": "Dane Myers",
      "bWAR": 0.14
    },
    {
      "Name": "Elly De La Cruz",
      "bWAR": 1.43
    },
    {
      "Name": "Eugenio Su\u00e1rez",
      "bWAR": -0.08
    },
    {
      "Name": "JJ Bleday",
      "bWAR": 0.19
    },
    {
      "Name": "Jose Trevino",
      "bWAR": -0.08
    },
    {
      "Name": "Ke'Bryan Hayes",
      "bWAR": -0.25
    },
    {
      "Name": "Matt McLain",
      "bWAR": -0.43
    },
    {
      "Name": "Nathaniel Lowe",
      "bWAR": 0.57
    },
    {
      "Name": "Noelvi Marte",
      "bWAR": -0.24
    },
    {
      "Name": "P.J. Higgins",
      "bWAR": -0.04
    },
    {
      "Name": "Rece Hinds",
      "bWAR": -0.3
    },
    {
      "Name": "Sal Stewart",
      "bWAR": 1.16
    },
    {
      "Name": "Spencer Steer",
      "bWAR": -0.25
    },
    {
      "Name": "TJ Friedl",
      "bWAR": -0.09
    },
    {
      "Name": "Tyler Stephenson",
      "bWAR": 0.29
    },
    {
      "Name": "Will Benson",
      "bWAR": -0.34
    }
  ],
  "pitch_2026": [
    {
      "Name": "Andrew Abbott",
      "bWAR": -0.1
    },
    {
      "Name": "Brady Singer",
      "bWAR": 0.34
    },
    {
      "Name": "Brandon Williamson",
      "bWAR": -0.09
    },
    {
      "Name": "Brock Burke",
      "bWAR": 0.45
    },
    {
      "Name": "Chase Burns",
      "bWAR": 1.38
    },
    {
      "Name": "Connor Phillips",
      "bWAR": 0.88
    },
    {
      "Name": "Emilio Pag\u00e1n",
      "bWAR": -0.03
    },
    {
      "Name": "Graham Ashcraft",
      "bWAR": 0.86
    },
    {
      "Name": "Jose Franco",
      "bWAR": -0.13
    },
    {
      "Name": "Jose Trevino",
      "bWAR": -0.15
    },
    {
      "Name": "Kyle Nicolas",
      "bWAR": -0.17
    },
    {
      "Name": "Luis Mey",
      "bWAR": 0.0
    },
    {
      "Name": "P.J. Higgins",
      "bWAR": 0.04
    },
    {
      "Name": "Pierce Johnson",
      "bWAR": 0.23
    },
    {
      "Name": "Rhett Lowder",
      "bWAR": 1.17
    },
    {
      "Name": "Sam Moll",
      "bWAR": 0.26
    },
    {
      "Name": "Tony Santillan",
      "bWAR": 0.72
    }
  ]
}